LICENSE
MANIFEST.in
README.rst
setup.py
bin/pdfebc
pdfebc/__init__.py
pdfebc/cli.py
pdfebc/core.py
pdfebc/main.py
pdfebc/utils.py
pdfebc.egg-info/PKG-INFO
pdfebc.egg-info/SOURCES.txt
pdfebc.egg-info/dependency_links.txt
pdfebc.egg-info/requires.txt
pdfebc.egg-info/top_level.txt