Metadata-Version: 1.1
Name: pdfebc
Version: 0.1.2
Summary: Application to compress PDF documents into an ebook reader-friendly size.
Home-page: https://github.com/slarse/pdfebc
Author: Simon Larsén
Author-email: slarse@kth.se
License: MIT License
